{
  "id": "81262334c5614333aa3833c167e9af53",
  "answers": [
    {
      "elm": "droppable_1",
      "type": "simple",
      "markType": "item",
      "markedBy": "engine",
      "value": "droppable_1"
    },
    {
      "elm": "droppable_2",
      "type": "simple",
      "markType": "item",
      "markedBy": "engine",
      "value": "droppable_2"
    },
    {
      "elm": "droppable_3",
      "type": "simple",
      "markType": "item",
      "markedBy": "engine",
      "value": "droppable_3"
    },
    {
      "elm": "droppable_4",
      "type": "simple",
      "markType": "item",
      "markedBy": "engine",
      "value": "droppable_4"
    }
  ]
}